tgedr/pipeline/source/__init__.py
tgedr/pipeline/source/ticker_live_lorikeet.py
tgedr_pipeline_source-0.0.3.dist-info/LICENSE
tgedr_pipeline_source-0.0.3.dist-info/METADATA
tgedr_pipeline_source-0.0.3.dist-info/WHEEL
tgedr_pipeline_source-0.0.3.dist-info/top_level.txt
tgedr_pipeline_source-0.0.3.dist-info/RECORD
